[
  {
    "x": 1683,
    "y": 794,
    "button": "Button.left",
    "timeMs": 1765790970024
  },
  {
    "x": 1225,
    "y": 1032,
    "button": "Button.left",
    "timeMs": 1765790976513
  },
  {
    "x": 934,
    "y": 919,
    "button": "Button.left",
    "timeMs": 1765790977730
  },
  {
    "x": 1165,
    "y": 558,
    "button": "Button.left",
    "timeMs": 1765790995601
  },
  {
    "x": 1032,
    "y": 669,
    "button": "Button.left",
    "timeMs": 1765790997113
  },
  {
    "x": 933,
    "y": 694,
    "button": "Button.left",
    "timeMs": 1765791003714
  },
  {
    "x": 1148,
    "y": 72,
    "button": "Button.left",
    "timeMs": 1765791008169
  },
  {
    "x": 1041,
    "y": 79,
    "button": "Button.left",
    "timeMs": 1765791010545
  },
  {
    "x": 333,
    "y": 605,
    "button": "Button.left",
    "timeMs": 1765791012553
  },
  {
    "x": 333,
    "y": 605,
    "button": "Button.left",
    "timeMs": 1765791012713
  },
  {
    "x": 826,
    "y": 577,
    "button": "Button.left",
    "timeMs": 1765791013345
  },
  {
    "x": 855,
    "y": 551,
    "button": "Button.left",
    "timeMs": 1765791014489
  },
  {
    "x": 1376,
    "y": 364,
    "button": "Button.left",
    "timeMs": 1765791014817
  },
  {
    "x": 1391,
    "y": 695,
    "button": "Button.left",
    "timeMs": 1765791015097
  },
  {
    "x": 890,
    "y": 663,
    "button": "Button.left",
    "timeMs": 1765791015393
  },
  {
    "x": 1071,
    "y": 456,
    "button": "Button.left",
    "timeMs": 1765791015681
  },
  {
    "x": 1314,
    "y": 707,
    "button": "Button.left",
    "timeMs": 1765791015929
  },
  {
    "x": 559,
    "y": 918,
    "button": "Button.left",
    "timeMs": 1765791018977
  },
  {
    "x": 1280,
    "y": 445,
    "button": "Button.left",
    "timeMs": 1765791023985
  },
  {
    "x": 1262,
    "y": 681,
    "button": "Button.left",
    "timeMs": 1765791024481
  },
  {
    "x": 772,
    "y": 918,
    "button": "Button.left",
    "timeMs": 1765791026769
  },
  {
    "x": 1816,
    "y": 645,
    "button": "Button.left",
    "timeMs": 1765791027873
  },
  {
    "x": 1177,
    "y": 542,
    "button": "Button.left",
    "timeMs": 1765791029169
  },
  {
    "x": 50,
    "y": 78,
    "button": "Button.left",
    "timeMs": 1765791031642
  },
  {
    "x": 399,
    "y": 367,
    "button": "Button.left",
    "timeMs": 1765791033049
  },
  {
    "x": 404,
    "y": 351,
    "button": "Button.left",
    "timeMs": 1765791033345
  },
  {
    "x": 404,
    "y": 351,
    "button": "Button.left",
    "timeMs": 1765791033497
  },
  {
    "x": 454,
    "y": 642,
    "button": "Button.left",
    "timeMs": 1765791034553
  },
  {
    "x": 454,
    "y": 642,
    "button": "Button.left",
    "timeMs": 1765791034697
  },
  {
    "x": 1094,
    "y": 692,
    "button": "Button.left",
    "timeMs": 1765791036057
  },
  {
    "x": 1094,
    "y": 692,
    "button": "Button.left",
    "timeMs": 1765791036225
  },
  {
    "x": 701,
    "y": 631,
    "button": "Button.left",
    "timeMs": 1765791057962
  }
]